mtgdeck/__init__.py
mtgdeck/__main__.py
mtgdeck/decoder.py
mtgdeck/encoder.py
mtgdeck/base/__init__.py
mtgdeck/base/decoder.py
mtgdeck/base/encoder.py
mtgdeck-0.2.0.dist-info/DESCRIPTION.rst
mtgdeck-0.2.0.dist-info/METADATA
mtgdeck-0.2.0.dist-info/RECORD
mtgdeck-0.2.0.dist-info/WHEEL
mtgdeck-0.2.0.dist-info/entry_points.txt
mtgdeck-0.2.0.dist-info/metadata.json
mtgdeck-0.2.0.dist-info/top_level.txt
mtgdeck-0.2.0.dist-info/zip-safe
