Metadata-Version: 2.0
Name: mtgdeck
Version: 0.2.0
Summary: MTG deck list decoder and encoder library and application
Home-page: https://github.com/pedros/mtgdeck
Author: Pedro Silva
Author-email: psilva+git@pedrosilva.pt
License: GPLv3
Download-URL: https://github.com/pedros/mtgdeck/archive/0.2.0.tar.gz
Keywords: magic-the-gathering,parser,encoder-decoder,command-line-app,library python3
Platform: UNKNOWN
Classifier: Development Status :: 4 - Beta
Classifier: Environment :: Console
Classifier: Intended Audience :: Developers
Classifier: Intended Audience :: End Users/Desktop
Classifier: License :: OSI Approved :: GNU General Public License v3 (GPLv3)
Classifier: Operating System :: OS Independent
Classifier: Programming Language :: Python :: 3 :: Only
Classifier: Programming Language :: Python :: 3.4
Classifier: Programming Language :: Python :: 3.5
Classifier: Programming Language :: Python :: 3.6
Classifier: Topic :: Games/Entertainment
Classifier: Topic :: Software Development :: Libraries
Classifier: Topic :: Software Development :: Libraries :: Python Modules
Classifier: Topic :: Text Processing :: Filters
Classifier: Topic :: Utilities
Requires-Dist: pyparsing
Requires-Dist: defusedxml
